mt/gl/__init__.py
mt/glfw/__init__.py
mt/opengl/__init__.py
mt/opengl/version.py
mtopengl-0.1.0.dist-info/LICENSE
mtopengl-0.1.0.dist-info/METADATA
mtopengl-0.1.0.dist-info/WHEEL
mtopengl-0.1.0.dist-info/top_level.txt
mtopengl-0.1.0.dist-info/RECORD
